{
	"agcgw_all":{
		"CN":"connect-drcn.hispace.hicloud.com",
		"CN_back":"connect-drcn.dbankcloud.cn",
		"DE":"connect-dre.hispace.hicloud.com",
		"DE_back":"connect-dre.dbankcloud.cn",
		"RU":"connect-drru.hispace.hicloud.com",
		"RU_back":"connect-drru.dbankcloud.cn",
		"SG":"connect-dra.hispace.hicloud.com",
		"SG_back":"connect-dra.dbankcloud.cn"
	},
	"client":{
		"cp_id":"1340007000017815958",
		"product_id":"737518067793553203",
		"client_id":"713934948800676864",
		"client_secret":"1F85A7D69BA6FBE226F6F9E4BA0B2A999BA4D793449B4D105FD8DBBC73C58081",
		"project_id":"737518067793553203",
		"app_id":"104727557",
		"api_key":"CwEAAAAAW827fXX5fYf51nkIXlz5iOgIFBPaE+4E60oKR/CNz9voJ7vfPQ/GEjnKOsF+Z+UubEjvYpTXGYDB91+sFPfNccnpIlo=",
		"package_name":"ru.vasic2000.myapplication.huawei"
	},
	"oauth_client":{
		"client_id":"104727557",
		"client_type":1
	},
	"app_info":{
		"app_id":"104727557",
		"package_name":"ru.vasic2000.myapplication.huawei"
	},
	"configuration_version":"3.0",
	"appInfos":[
		{
			"package_name":"ru.vasic2000.myapplication.huawei",
			"client":{
				"app_id":"104727557"
			},
			"app_info":{
				"package_name":"ru.vasic2000.myapplication.huawei",
				"app_id":"104727557"
			},
			"oauth_client":{
				"client_type":1,
				"client_id":"104727557"
			}
		}
	]
}